README.md
setup.cfg
setup.py
cieloApi3/__init__.py
cieloApi3/address.py
cieloApi3/cieloEcommerce.py
cieloApi3/creditCard.py
cieloApi3/customer.py
cieloApi3/environment.py
cieloApi3/merchant.py
cieloApi3/objectJSON.py
cieloApi3/payment.py
cieloApi3/recurrentPayment.py
cieloApi3/sale.py
cieloApi3/request/__init__.py
cieloApi3/request/base.py
cieloApi3/request/createCardToken.py
cieloApi3/request/createSale.py
cieloApi3/request/deactivateRecorrency.py
cieloApi3/request/queryRecorrency.py
cieloApi3/request/querySale.py
cieloApi3/request/reactivateRecorrency.py
cieloApi3/request/updateSale.py
cieloApi3_py3.egg-info/PKG-INFO
cieloApi3_py3.egg-info/SOURCES.txt
cieloApi3_py3.egg-info/dependency_links.txt
cieloApi3_py3.egg-info/requires.txt
cieloApi3_py3.egg-info/top_level.txt